<?xml version="1.0" encoding="utf-8" ?>
<dwsync>
<file name="default.php" server="ftp.dowalo.com" local="131293682419638449" remote="131293338000000000" Dst="0" />
<file name="default.featured.items.php" server="ftp.dowalo.com" local="131266264023062352" remote="131266725000000000" Dst="0" />
<file name="default.header.php" server="ftp.dowalo.com" local="131262618174344391" remote="131262326400000000" Dst="0" />
<file name="default.items.php" server="ftp.dowalo.com" local="131287864974933853" remote="131287476000000000" Dst="0" />
<file name="item.php" server="ftp.dowalo.com" local="131285276071811127" remote="131284885200000000" Dst="0" />
<file name="default.others.php" server="ftp.dowalo.com" local="131263695023934536" remote="131263300200000000" Dst="0" />
<file name="default.items.featured.php" server="ftp.dowalo.com" local="131266933588758072" remote="131266725000000000" Dst="0" />
<file name="default.all.items.php" server="ftp.dowalo.com" local="131293696885172643" remote="131293338600000000" Dst="0" />
</dwsync>